{"nodes": [{"id": "paths", "label": "paths.ts", "file_type": "code", "source_file": "baoyu-skills\\skills\\baoyu-url-to-markdown\\scripts\\paths.ts", "source_location": "L1"}, {"id": "paths_resolveuserdataroot", "label": "resolveUserDataRoot()", "file_type": "code", "source_file": "baoyu-skills\\skills\\baoyu-url-to-markdown\\scripts\\paths.ts", "source_location": "L9"}, {"id": "paths_resolveurltomarkdowndatadir", "label": "resolveUrlToMarkdownDataDir()", "file_type": "code", "source_file": "baoyu-skills\\skills\\baoyu-url-to-markdown\\scripts\\paths.ts", "source_location": "L19"}, {"id": "paths_resolveurltomarkdownchromeprofiledir", "label": "resolveUrlToMarkdownChromeProfileDir()", "file_type": "code", "source_file": "baoyu-skills\\skills\\baoyu-url-to-markdown\\scripts\\paths.ts", "source_location": "L25"}], "edges": [{"source": "paths", "target": "node_os", "relation": "imports_from", "confidence": "EXTRACTED", "source_file": "baoyu-skills\\skills\\baoyu-url-to-markdown\\scripts\\paths.ts", "source_location": "L1", "weight": 1.0}, {"source": "paths", "target": "node_path", "relation": "imports_from", "confidence": "EXTRACTED", "source_file": "baoyu-skills\\skills\\baoyu-url-to-markdown\\scripts\\paths.ts", "source_location": "L2", "weight": 1.0}, {"source": "paths", "target": "node_process", "relation": "imports_from", "confidence": "EXTRACTED", "source_file": "baoyu-skills\\skills\\baoyu-url-to-markdown\\scripts\\paths.ts", "source_location": "L3", "weight": 1.0}, {"source": "paths", "target": "paths_resolveuserdataroot", "relation": "contains", "confidence": "EXTRACTED", "source_file": "baoyu-skills\\skills\\baoyu-url-to-markdown\\scripts\\paths.ts", "source_location": "L9", "weight": 1.0}, {"source": "paths", "target": "paths_resolveurltomarkdowndatadir", "relation": "contains", "confidence": "EXTRACTED", "source_file": "baoyu-skills\\skills\\baoyu-url-to-markdown\\scripts\\paths.ts", "source_location": "L19", "weight": 1.0}, {"source": "paths", "target": "paths_resolveurltomarkdownchromeprofiledir", "relation": "contains", "confidence": "EXTRACTED", "source_file": "baoyu-skills\\skills\\baoyu-url-to-markdown\\scripts\\paths.ts", "source_location": "L25", "weight": 1.0}, {"source": "paths_resolveurltomarkdownchromeprofiledir", "target": "paths_resolveuserdataroot", "relation": "calls", "confidence": "INFERRED", "source_file": "baoyu-skills\\skills\\baoyu-url-to-markdown\\scripts\\paths.ts", "source_location": "L28", "weight": 0.8}]}